nostpy_cli/__init__.py
nostpy_cli/create_event.py
nostpy_cli/kind4.py
nostpy_cli/main.py
nostpy_cli-0.3.3.dist-info/LICENSE
nostpy_cli-0.3.3.dist-info/METADATA
nostpy_cli-0.3.3.dist-info/WHEEL
nostpy_cli-0.3.3.dist-info/entry_points.txt
nostpy_cli-0.3.3.dist-info/top_level.txt
nostpy_cli-0.3.3.dist-info/RECORD
